methodical/main.py
methodical-0.1.1.dist-info/licenses/LICENSE
methodical-0.1.1.dist-info/METADATA
methodical-0.1.1.dist-info/WHEEL
methodical-0.1.1.dist-info/entry_points.txt
methodical-0.1.1.dist-info/top_level.txt
methodical-0.1.1.dist-info/RECORD
