Metadata-Version: 2.4
Name: methodical
Version: 0.1.1
Summary: Scan a markdown file and create a table of content
Author-email: LaLinguette <LaLinguette@gmail.com>
License: MIT
Project-URL: Homepage, https://github.com/lalinguette/methodical
Requires-Python: >=3.12
License-File: LICENSE
Dynamic: license-file
